[
  {
    "packet": 0,
    "center_lat": 63.440717244279696,
    "center_lon": 10.352350573764609,
    "dir_A_enu": [
      0.8929868266977549,
      -0.45008280054260463,
      0.0
    ],
    "dir_B_enu": [
      -0.05846357206253977,
      0.9982895425384803,
      -0.0
    ],
    "channels_min": 180,
    "channels_max": 208,
    "n_channels": 16
  },
  {
    "packet": 60,
    "center_lat": 63.44073733089448,
    "center_lon": 10.352418876745727,
    "dir_A_enu": [
      0.9962212766980566,
      0.08685141250488743,
      0.0
    ],
    "dir_B_enu": [
      0.4753126244282326,
      0.8798169747505137,
      -0.0
    ],
    "channels_min": 180,
    "channels_max": 209,
    "n_channels": 13
  },
  {
    "packet": 30,
    "center_lat": 63.440722265933545,
    "center_lon": 10.352367649510482,
    "dir_A_enu": [
      0.8826415965775998,
      -0.4700466061902221,
      0.0
    ],
    "dir_B_enu": [
      -0.08089465524644318,
      0.9967226568873405,
      -0.0
    ],
    "channels_min": 180,
    "channels_max": 206,
    "n_channels": 18
  }
]